ddq_widgets/__init__.py
ddq_widgets/ddq_button.py
ddq_widgets/ddq_button_group.py
ddq_widgets/ddq_card.py
ddq_widgets/ddq_form.py
ddq_widgets/ddq_form_item.py
ddq_widgets/ddq_space.py
ddq_widgets/ddq_split_layout.py
ddq_widgets/ddq_table.py
ddq_widgets/ddq_text.py
ddq_widgets/ddq_textarea.py
ddq_widgets/ddq_toast.py
examples/__init__.py
examples/demo_card.py
examples/form_demo.py
ddq_tkinter_widgets-0.1.4.dist-info/METADATA
ddq_tkinter_widgets-0.1.4.dist-info/WHEEL
ddq_tkinter_widgets-0.1.4.dist-info/top_level.txt
ddq_tkinter_widgets-0.1.4.dist-info/RECORD
