Metadata-Version: 2.1
Name: ddq-tkinter-widgets
Version: 0.1.4
Summary: A collection of custom tkinter widgets
Home-page: https://github.com/zgq54457/ddq_tkinter
Author: ddq
Author-email: zgq54457@gmail.com
Classifier: Development Status :: 3 - Alpha
Classifier: Intended Audience :: Developers
Classifier: License :: OSI Approved :: MIT License
Classifier: Programming Language :: Python :: 3
Classifier: Programming Language :: Python :: 3.6
Classifier: Programming Language :: Python :: 3.7
Classifier: Programming Language :: Python :: 3.8
Classifier: Programming Language :: Python :: 3.9
Classifier: Programming Language :: Python :: 3.10
Requires-Python: >=3.6
